jmxquery/JMXQuery-0.1.8.jar
jmxquery/__init__.py
jmxquery-0.6.0.dist-info/LICENSE.txt
jmxquery-0.6.0.dist-info/METADATA
jmxquery-0.6.0.dist-info/WHEEL
jmxquery-0.6.0.dist-info/top_level.txt
jmxquery-0.6.0.dist-info/RECORD
