Metadata-Version: 2.1
Name: jmxquery
Version: 0.6.0
Summary: A JMX Interface for Python to Query runtime metrics in a JVM
Home-page: https://github.com/dgildeh/jmxquery
Author: David Gildeh
Author-email: david.gildeh@outlyer.com
License: UNKNOWN
Keywords: java,jmx,metrics,monitoring
Platform: UNKNOWN
